Workbook

Sheet START HERE
B2: askakshay.com | Business Finance Launch Kit
B4: Business Viability Calculator
B5: Know if your idea makes money — before you spend a rupee on it.
B8: HOW TO USE — 5 TABS, 15 MINUTES
B9: STEP 1 → START HERE
B10: You are here. Read the color guide below before editing anything.
B11: STEP 2 → IDEA SNAPSHOT
B12: Enter your business name, price, target customer, and monthly sales estimate.
B13: STEP 3 → BREAK-EVEN ENGINE
B14: Enter fixed and variable costs. Break-even auto-calculates.
B15: STEP 4 → RUNWAY PLANNER
B16: Enter capital and personal expenses. 12-month cash flow builds automatically.
... B28: Red text = High risk / rethink required

Sheet IDEA SNAPSHOT
B1: askakshay.com | IDEA SNAPSHOT
B2: IDEA SNAPSHOT
B4: Define your business before building it. Vague answers give useless results.
B6: YOUR BUSINESS
B7: Business / Idea Name | C7: e.g. Finance Kits by Akshay | D7: What will you call it?
B8: What do you sell? | C8: e.g. Digital workbooks + Google Sheets | D8: Product / Service / Both?
B9: Who is your target customer? | C9: e.g. Indian first-time entrepreneurs 25-35 | D9: Be specific — not 'everyone'
B10: Revenue model | C10: e.g. One-time digital download | D10: One-time / Subscription / Service
B11: Primary sales channel | C11: e.g. askakshay.com + Instagram | D11: Where will customers find & buy?
B12: Selling currency | C12: INR | D12: INR / MYR / USD
B14: YOUR PRICING
B15: Price per unit / sale (Rs.) | C15: 2999 | D15: What will you charge per transaction?
B16: Estimated units sold — Month 1 | C16: 10 | D16: Conservative guess — stress-tested in Tab 3
B17: Expected refund / discount rate (%) | C17: 0.05 | D17: e.g. 0.05 = 5% of sales refunded

Sheet BREAK-EVEN ENGINE
B1: askakshay.com | BREAK-EVEN ENGINE
B2: BREAK-EVEN ENGINE
B4: How many sales do you need to cover all costs? Enter actuals or honest estimates.
B6: FIXED COSTS (monthly — you pay these regardless of sales)
B7: Domain + hosting | C7: 500 | D7: Rs. / month
B8: Design tools (Canva Pro etc.) | C8: 0 | D8: Rs. / month
B9: Payment gateway flat fee | C9: 0 | D9: Rs. / month
B10: Phone / internet (business share) | C10: 500 | D10: Rs. / month
B11: Other fixed cost 1 | C11: 0 | D11: Rs. / month
B12: Other fixed cost 2 | C12: 0 | D12: Rs. / month
B13: TOTAL FIXED COSTS | C13: =SUM(C7:C12) -> 1000 | D13: Rs. / month
B15: VARIABLE COSTS (per unit sold)
B16: Payment gateway % fee (e.g. 0.02 = 2%) | C16: 0.02 | D16: per unit
B17: Platform / marketplace fee % | C17: 0 | D17: per unit
B18: Delivery / fulfilment cost per unit | C18: 0 | D18: per unit
B19: Other variable cost per unit | C19: 0 | D19: per unit
B20: TOTAL VARIABLE COST PER UNIT | C20: ='IDEA SNAPSHOT'!C15*(C16+C17)+C18+C19 -> 59.98 | D20: per unit
B22: CONTRIBUTION MARGIN & BREAK-EVEN
B23: Selling price per unit (Rs.) | C23: ='IDEA SNAPSHOT'!C15 -> 2999
B24: Variable cost per unit (Rs.) | C24: =C20 -> 59.98
B25: Contribution margin per unit (Rs.) | C25: =C23-C24 -> 2939.02
B26: Contribution margin (%) | C26: =IF(C23>0,C25/C23,0) -> 0.98
B27: Monthly fixed costs (Rs.) | C27: =C13 -> 1000
B28: BREAK-EVEN UNITS / MONTH | C28: =IF(C25>0,CEILING(C27/C25,1),"N/A") -> 1 | D28: KEY OUTPUT
B29: BREAK-EVEN REVENUE / MONTH (Rs.) | C29: =IF(ISNUMBER(C28),C28*C23,"N/A") -> 2999 | D29: KEY OUTPUT

Sheet RUNWAY PLANNER
B1: askakshay.com | 12-MONTH RUNWAY PLANNER
B2: 12-MONTH RUNWAY PLANNER
B4: How long can you survive before the business must support itself?
B6: CAPITAL & BURN ASSUMPTIONS
B7: Starting capital / savings allocated (Rs.) | C7: 50000 | D7: Amount you're willing to put in
B8: Your monthly salary / other income (Rs.) | C8: 0 | D8: Include if you're a part-time founder
B9: Personal monthly expenses (Rs.) | C9: 30000 | D9: Rent, food, EMI — be honest
B10: Expected units sold — Month 1 | C10: 5 | D10: Start conservative
B11: Monthly unit growth rate (%) | C11: 0.1 | D11: e.g. 0.10 = 10% each month
B12: Price per unit (Rs.) | C12: ='IDEA SNAPSHOT'!C15 -> 2999 | D12: Auto-pulled from Tab 2
B13: Variable cost per unit (Rs.) | C13: ='BREAK-EVEN ENGINE'!C20 -> 59.98 | D13: Auto-pulled from Tab 3
B14: Monthly fixed costs (Rs.) | C14: ='BREAK-EVEN ENGINE'!C13 -> 1000 | D14: Auto-pulled from Tab 3
B16: MONTH-BY-MONTH PROJECTION
B17: MONTH | C17: UNITS SOLD | D17: REVENUE (Rs.) | E17: VARIABLE COSTS (Rs.) | F17: FIXED COSTS (Rs.) | G17: NET CASH (Rs.)
B18: Month 1 | C18: =C10 -> 5 | D18: =C18*C12 -> 14995 | E18: =C18*C13 -> 299.9 | F18: =C14 -> 1000 | G18: =D18-E18-F18+C8-C9 -> -16304.9
B19: Month 2 | C19: =C18*(1+C11) -> 5.5 | D19: =C19*C12 -> 16494.5 | E19: =C19*C13 -> 329.89 | F19: =C14 -> 1000 | G19: =D19-E19-F19+C8-C9 -> -14835.39
B20: Month 3 | C20: =C19*(1+C11) -> 6.05 | D20: =C20*C12 -> 18143.95 | E20: =C20*C13 -> 362.879 | F20: =C14 -> 1000 | G20: =D20-E20-F20+C8-C9 -> -13218.929
B21: Month 4 | C21: =C20*(1+C11) -> 6.655 | D21: =C21*C12 -> 19958.345 | E21: =C21*C13 -> 399.1669 | F21: =C14 -> 1000 | G21: =D21-E21-F21+C8-C9 -> -11440.822
B22: Month 5 | C22: =C21*(1+C11) -> 7.3205 | D22: =C22*C12 -> 21954.179 | E22: =C22*C13 -> 439.08359 | F22: =C14 -> 1000 | G22: =D22-E22-F22+C8-C9 -> -9484.9041
B23: Month 6 | C23: =C22*(1+C11) -> 8.05255 | D23: =C23*C12 -> 24149.597 | E23: =C23*C13 -> 482.99195 | F23: =C14 -> 1000 | G23: =D23-E23-F23+C8-C9 -> -7333.3945
B24: Month 7 | C24: =C23*(1+C11) -> 8.857805 | D24: =C24*C12 -> 26564.557 | E24: =C24*C13 -> 531.29114 | F24: =C14 -> 1000 | G24: =D24-E24-F24+C8-C9 -> -4966.7339
B25: Month 8 | C25: =C24*(1+C11) -> 9.7435855 | D25: =C25*C12 -> 29221.013 | E25: =C25*C13 -> 584.42026 | F25: =C14 -> 1000 | G25: =D25-E25-F25+C8-C9 -> -2363.4073
B26: Month 9 | C26: =C25*(1+C11) -> 10.717944 | D26: =C26*C12 -> 32143.114 | E26: =C26*C13 -> 642.86228 | F26: =C14 -> 1000 | G26: =D26-E26-F26+C8-C9 -> 500.25192
B27: Month 10 | C27: =C26*(1+C11) -> 11.789738 | D27: =C27*C12 -> 35357.426 | E27: =C27*C13 -> 707.14851 | F27: =C14 -> 1000 | G27: =D27-E27-F27+C8-C9 -> 3650.2771
B28: Month 11 | C28: =C27*(1+C11) -> 12.968712 | D28: =C28*C12 -> 38893.168 | E28: =C28*C13 -> 777.86336 | F28: =C14 -> 1000 | G28: =D28-E28-F28+C8-C9 -> 7115.3048
B29: Month 12 | C29: =C28*(1+C11) -> 14.265584 | D29: =C29*C12 -> 42782.485 | E29: =C29*C13 -> 855.6497 | F29: =C14 -> 1000 | G29: =D29-E29-F29+C8-C9 -> 10926.835
B30: TOTAL (12 MONTHS) | C30: =SUM(C18:C29) -> 106.92142 | D30: =SUM(D18:D29) -> 320657.34 | E30: =SUM(E18:E29) -> 6413.1467 | F30: =SUM(F18:F29) -> 12000 | G30: =SUM(G18:G29) -> -57755.812
B32: RUNWAY SUMMARY
B33: Cumulative net cash after 12 months (Rs.) | C33: =C7+G30 -> -7755.8116
B34: Estimated runway before capital hits zero (months) | C34: =IF((C9-C8+C14)>0,ROUND(C7/(C9-C8+C14),1),"Self-sustaining") -> 1.6

Sheet VERDICT DASHBOARD
B1: askakshay.com | VERDICT DASHBOARD
B2: VERDICT DASHBOARD
B4: All outputs aggregate here. One signal. Plain English. No jargon.
B6: KEY METRICS SUMMARY
B7: Your selling price (Rs.) | C7: ='IDEA SNAPSHOT'!C15 -> 2999
B8: Your Month-1 sales estimate (units) | C8: ='IDEA SNAPSHOT'!C16 -> 10
B9: Break-even units / month | C9: ='BREAK-EVEN ENGINE'!C28 -> 1
B10: Break-even revenue / month (Rs.) | C10: ='BREAK-EVEN ENGINE'!C29 -> 2999
B11: Contribution margin (%) | C11: ='BREAK-EVEN ENGINE'!C26 -> 0.98
B12: 12-month cumulative net cash (Rs.) | C12: ='RUNWAY PLANNER'!C33 -> -7755.8116
B13: Estimated runway (months) | C13: ='RUNWAY PLANNER'!C34 -> 1.6
B15: YOUR VERDICT
B16: =IF(AND(ISNUMBER(C9),ISNUMBER(C13)),IF(AND(C9<=C8*0.5,C13>6),"GREEN | VIABLE — Break-even is within reach. Launch with confidence.",IF(C9>C8*2,"RED | HIGH RISK — Break-even requires 2x+ your Month-1 estimate. Fix first.","AMBER | MARGINAL — Close, but adjust pricing or costs before launching.")),"Fill in Tabs 2-4 to unlock your verdict.") -> AMBER | MARGINAL — Close, but adjust pricing or costs before launching.
B18: INTERPRETATION GUIDE
B19: GREEN | VIABLE | C19: Break-even is within 50% of your Month-1 target AND runway > 6 months. Launch. Track revenue weekly. Scale what works.
B20: AMBER | MARGINAL | C20: You're close but not comfortable. Fix one of: raise price / cut fixed costs / revise sales estimate upward before launching.
B21: RED | HIGH RISK | C21: Break-even requires 2x+ what you expect to sell. Rethink pricing, cost structure, or the idea itself before spending any money.
B23: Ship with numbers, not hope. | Get the full kit at askakshay.com
